[
  {
    "type": "headline",
    "position": 0,
    "coordinates": {
      "top": -12676.609375,
      "left": 365,
      "height": 414.3125,
      "width": 732.5
    },
    "link": "https://noticias.uol.com.br/eleicoes/2022/11/01/bolsonaro-discurso-eleicoes-derrota-lula.htm",
    "title": "Bolsonaro critica atos e defende direito de ir e vir; Ciro Nogueira dá início à transição",
    "summary": "Após 44 horas de silêncio, presidente faz discurso de 2 minutos"
  },
  {
    "type": "article",
    "position": 0,
    "coordinates": {
      "top": -12062.90625,
      "left": 365,
      "height": 563.359375,
      "width": 224.15625
    },
    "link": "https://www1.folha.uol.com.br/mercado/2022/11/prf-manda-agentes-ficharem-nome-de-donos-de-caminhoes-para-inquerito-de-moraes.shtml",
    "title": "PRF manda agentes ficharem nome de donos de caminhões para inquérito de Moraes"
  },
  {
    "type": "article",
    "position": 1,
    "coordinates": {
      "top": -11475.546875,
      "left": 365,
      "height": 323.875,
      "width": 224.15625
    },
    "link": "https://noticias.uol.com.br/confere/ultimas-noticias/2022/11/01/mentiras-sobre-artigo-142-da-constituicao-federal.htm",
    "title": "Fake news sobre artigo 142 da Constituição incluem espera de 72 horas e intervenção"
  },
  {
    "type": "article",
    "position": 2,
    "coordinates": {
      "top": -12062.90625,
      "left": 619.15625,
      "height": 544.171875,
      "width": 224.15625
    },
    "link": "https://noticias.uol.com.br/politica/ultimas-noticias/2022/11/01/bolsonaro-vai-ao-stf-apos-pronunciamento-sobre-eleicoes.htm",
    "title": "Bolsonaro diz no STF que eleição 'acabou' e sinaliza que aceita a derrota, afirma Fachin"
  },
  {
    "type": "article",
    "position": 3,
    "coordinates": {
      "top": -11494.734375,
      "left": 619.15625,
      "height": 341.671875,
      "width": 224.15625
    },
    "link": "https://noticias.uol.com.br/colunas/carlos-madeiro/2022/11/01/ala-evangelica-ignora-lideres-e-apoia-bloqueios-pelo-pais-agora-e-guerra.htm",
    "title": "Ala evangélica ignora líderes e apoia bloqueios pelo país: 'Agora é guerra'"
  }
]
