[
  {
    "type": "headline",
    "position": 0,
    "coordinates": {
      "top": -4198,
      "left": 347.65625,
      "height": 661.171875,
      "width": 606.328125
    },
    "link": "https://g1.globo.com/saude/coronavirus/vacinas/noticia/2022/10/16/a-cada-2-dias-1-crianca-com-menos-de-5-anos-morre-de-covid-no-brasil-grupo-esta-sem-vacina-e-governo-nao-diz-quando-tera-doses-da-pfizer.ghtml",
    "hat": "Campanha de vacinação",
    "title": "A cada 2 dias, 1 criança com menos de 5 anos morre de Covid; vacina não foi liberada pelo governo"
  },
  {
    "type": "headline",
    "position": 1,
    "coordinates": {
      "top": -4198,
      "left": 965.984375,
      "height": 324.578125,
      "width": 606.328125
    },
    "link": "https://g1.globo.com/pr/oeste-sudoeste/noticia/2022/10/16/fotos-mostram-cataratas-do-iguacu-apos-segunda-maior-vazao-de-agua-desde-1997-veja-galeria.ghtml",
    "hat": "É muita água",
    "title": "FOTOS mostram Cataratas após 2ª maior vazão desde 1997"
  },
  {
    "type": "headline",
    "position": 2,
    "coordinates": {
      "top": -3861.421875,
      "left": 965.984375,
      "height": 324.59375,
      "width": 606.328125
    },
    "link": "https://ge.globo.com/skate/noticia/2022/10/16/rayssa-leal-brilha-e-e-bicampea-do-stu-open-rio.ghtml",
    "hat": "Fadinha",
    "title": "Rayssa Leal brilha e é bicampeã do STU Open Rio"
  },
  {
    "type": "article",
    "position": 0,
    "coordinates": {
      "top": -3456.828125,
      "left": 348.65625,
      "height": 299.640625,
      "width": 842.203125
    },
    "link": "https://g1.globo.com/politica/blog/andreia-sadi/post/2022/10/16/moraes-manda-plataformas-e-campanha-de-lula-excluirem-video-com-fala-de-bolsonaro-sobre-meninas-venezuelanas.ghtml",
    "hat": "Blog da Andréia Sadi",
    "title": "Moraes manda excluir e proíbe PT de usar vídeo de Bolsonaro com fala 'pintou um clima'",
    "category": "Blog da Andréia Sadi"
  },
  {
    "type": "article",
    "position": 1,
    "coordinates": {
      "top": -3125.1875,
      "left": 348.65625,
      "height": 246.171875,
      "width": 842.203125
    },
    "link": "https://g1.globo.com/rj/rio-de-janeiro/eleicoes/2022/noticia/2022/10/16/simone-tebet-pede-votos-para-lula-no-leblon-e-canta-jingle-contra-bolsonaro.ghtml",
    "title": "Tebet faz campanha para Lula na Zona Sul do Rio",
    "category": "Eleições 2022 no Rio de Janeiro"
  }
]
