[
  {
    "type": "headline",
    "position": 0,
    "coordinates": {
      "top": -5874.890625,
      "left": 324,
      "height": 306,
      "width": 948
    },
    "link": "https://veja.abril.com.br/politica/lula-e-bolsonaro-a-guerra-de-versoes-sobre-o-empate-na-reta-final/",
    "hat": "Eleição",
    "title": "Lula e Bolsonaro travam guerra de versões sobre empate na reta final da campanha",
    "summary": "A uma semana do segundo turno, cada candidato tenta convencer o eleitor de que ele, e não o rival, está mais perto de ganhar; estratégia busca animar as militâncias e conquistar quem ainda não decidiu o voto"
  },
  {
    "type": "headline",
    "position": 1,
    "coordinates": {
      "top": -4813.921875,
      "left": 648,
      "height": 170,
      "width": 948
    },
    "link": "https://veja.abril.com.br/politica/quem-sao-os-17-milhoes-de-eleitores-que-podem-definir-o-2o-turno",
    "hat": "Reportagem de capa",
    "title": "Quem são os 17 milhões de eleitores indecisos que podem definir o 2º turno",
    "summary": "Como a imensa maioria já sabe em quem vai votar, o resultado do pleito passa por quem não escolheu ou pode mudar de lado, um grupo de votantes homogêneo e bem definido"
  },
  {
    "type": "headline",
    "position": 2,
    "coordinates": {
      "top": -3675.796875,
      "left": 324,
      "height": 220,
      "width": 948
    },
    "link": "https://veja.abril.com.br/paginas-amarelas/sergio-moro-a-volta-do-lula-seria-um-suicidio-moral-e-economico/",
    "hat": "Política",
    "title": "Sergio Moro: 'A volta do Lula seria um suicídio moral e econômico'",
    "summary": "Senador eleito explica reaproximação com Bolsonaro, dispara contra o petista e diz que a Justiça passa a impressão de que o crime compensa"
  },
  {
    "type": "article",
    "position": 0,
    "coordinates": {
      "top": -5544.890625,
      "left": 324,
      "height": 225.984375,
      "width": 191.984375
    },
    "link": "https://veja.abril.com.br/politica/em-investigacao-sobre-pandemia-justica-descobre-propina-com-nota-fiscal/",
    "hat": "Pandemia",
    "title": "Em investigação, Justiça descobre propina com nota fiscal"
  },
  {
    "type": "article",
    "position": 1,
    "coordinates": {
      "top": -5544.890625,
      "left": 539.984375,
      "height": 225.984375,
      "width": 191.984375
    },
    "link": "https://veja.abril.com.br/politica/lider-caminhoneiro-nega-apelo-por-folga-para-voto-no-2o-turno-absurdo/",
    "hat": "Estratégia",
    "title": "Líder caminhoneiro nega apelo por folga para voto no 2º turno: ‘Absurdo’"
  }
]
